{
    "cluster": "staging-1",
    "serviceName": "mysql-service",
    "taskDefinition": "mysql-task",
    "desiredCount": 1,
    "clientToken": "",
    "launchType": "EC2",
    "deploymentConfiguration": {
        "maximumPercent": 200,
        "minimumHealthyPercent": 100
    },
    "placementStrategy": [
        {
            "type": "spread",
            "field": ""
        }
    ],
    "networkConfiguration": {
        "awsvpcConfiguration": {
            "subnets": [
                ""
            ],
            "securityGroups": [
                ""
            ],
            "assignPublicIp": "ENABLED"
        }
    },
    "schedulingStrategy": "REPLICA"
}
